[
  {
    "id": 51,
    "name": "Milim Nava",
    "rarity": "Legendary",
    "price": 600,
    "faction": "Demon Lords",
    "image_url": "https://static.wikia.nocookie.net/tensei-shitara/images/2/2d/Milim_Anime.png"
  },
  {
    "id": 52,
    "name": "Diablo",
    "rarity": "Legendary",
    "price": 550,
    "faction": "Demon Lords",
    "image_url": "https://static.wikia.nocookie.net/tensei-shitara/images/9/9a/Diablo_Anime.png"
  },
  {
    "id": 53,
    "name": "Leon Cromwell",
    "rarity": "Legendary",
    "price": 650,
    "faction": "Demon Lords",
    "image_url": "https://static.wikia.nocookie.net/tensei-shitara/images/8/8f/Leon_Anime.png"
  },
  {
    "id": 54,
    "name": "Guy Crimson",
    "rarity": "Legendary",
    "price": 700,
    "faction": "Demon Lords",
    "image_url": "https://static.wikia.nocookie.net/tensei-shitara/images/1/1a/Guy_Crimson.png"
  },
  {
    "id": 55,
    "name": "Ramiris",
    "rarity": "Epic",
    "price": 400,
    "faction": "Demon Lords",
    "image_url": "https://static.wikia.nocookie.net/tensei-shitara/images/2/2a/Ramiris_Anime.png"
  },
  {
   "id": 56,
    "name": "Dagruel",
    "rarity": "Legendary",
    "price": 650,
    "faction": "Demon Lords",
    "image_url": "https://static.wikia.nocookie.net/tensei-shitara/images/3/3a/Dagruel_Anime.png"
  },
  {
    "id": 57,
    "name": "Luminous Valentine",
    "rarity": "Legendary",
    "price": 700,
    "faction": "Demon Lords",
    "image_url": "https://static.wikia.nocookie.net/tensei-shitara/images/4/4a/Luminous_Valentine.png"
  },
  {
    "id": 58,
    "name": "Roy Valentine",
    "rarity": "Epic",
    "price": 380,
    "faction": "Demon Lords",
    "image_url": "https://static.wikia.nocookie.net/tensei-shitara/images/5/5a/Roy_Valentine.png"
  },
  {
    "id": 59,
    "name": "Kazaream",
    "rarity": "Epic",
    "price": 370,
    "faction": "Demon Lords",
    "image_url": "https://static.wikia.nocookie.net/tensei-shitara/images/6/6a/Kazaream.png"
  },
  {
    "id": 60,
    "name": "Carrion",
    "rarity": "Epic",
    "price": 400,
    "faction": "Demon Lords",
    "image_url": "https://static.wikia.nocookie.net/tensei-shitara/images/7/7a/Carrion.png"
  },
  {
    "id": 61,
    "name": "Frey",
    "rarity": "Epic",
    "price": 380,
    "faction": "Demon Lords",
    "image_url": "https://static.wikia.nocookie.net/tensei-shitara/images/8/8a/Frey.png"
  },
  {
    "id": 62,
    "name": "Orcus",
    "rarity": "Rare",
    "price": 300,
    "faction": "Demon Lords",
    "image_url": "https://static.wikia.nocookie.net/tensei-shitara/images/9/9a/Orcus.png"
  },
  {
    "id": 63,
    "name": "Clayman",
    "rarity": "Epic",
    "price": 350,
    "faction": "Demon Lords",
    "image_url": "https://static.wikia.nocookie.net/tensei-shitara/images/1/1a/Clayman.png"
  },
  {
    "id": 64,
    "name": "Adalman",
    "rarity": "Rare",
    "price": 280,
    "faction": "Demon Lords",
    "image_url": "https://static.wikia.nocookie.net/tensei-shitara/images/2/2a/Adalman.png"
  },
  {
    "id": 65,
    "name": "Ultima",
    "rarity": "Legendary",
    "price": 650,
    "faction": "Demon Lords",
    "image_url": "https://static.wikia.nocookie.net/tensei-shitara/images/3/3a/Ultima.png"
  },
  {
    "id": 66,
    "name": "Testarossa",
    "rarity": "Legendary",
    "price": 650,
    "faction": "Demon Lords",
    "image_url": "https://static.wikia.nocookie.net/tensei-shitara/images/4/4a/Testarossa.png"
  },
  {
    "id": 67,
    "name": "Carrera",
    "rarity": "Legendary",
    "price": 650,
    "faction": "Demon Lords",
    "image_url": "https://static.wikia.nocookie.net/tensei-shitara/images/5/5a/Carrera.png"
  },
  {
    "id": 68,
    "name": "Zegion",
    "rarity": "Legendary",
    "price": 700,
    "faction": "Demon Lords",
    "image_url": "https://static.wikia.nocookie.net/tensei-shitara/images/6/6a/Zegion.png"
  },
  {
    "id": 69,
    "name": "Apito",
    "rarity": "Rare",
    "price": 280,
    "faction": "Demon Lords",
    "image_url": "https://static.wikia.nocookie.net/tensei-shitara/images/7/7a/Apito.png"
  },
  {
    "id": 70,
    "name": "Kumara",
    "rarity": "Epic",
    "price": 350,
    "faction": "Demon Lords",
    "image_url": "https://static.wikia.nocookie.net/tensei-shitara/images/8/8a/Kumara.png"
  },
  {
    "id": 71,
    "name": "Mephisto",
    "rarity": "Legendary",
    "price": 700,
    "faction": "Demon Lords",
    "image_url": "https://static.wikia.nocookie.net/tensei-shitara/images/9/9a/Mephisto.png"
  },
  {
    "id": 72,
    "name": "Valentine",
    "rarity": "Epic",
    "price": 380,
    "faction": "Demon Lords",
    "image_url": "https://static.wikia.nocookie.net/tensei-shitara/images/1/1a/Valentine.png"
  },
  {
    "id": 73,
    "name": "Dagura",
    "rarity": "Rare",
    "price": 300,
    "faction": "Demon Lords",
    "image_url": "https://static.wikia.nocookie.net/tensei-shitara/images/2/2a/Dagura.png"
  },
  {
    "id": 74,
    "name": "Lucia",
    "rarity": "Rare",
    "price": 280,
    "faction": "Demon Lords",
    "image_url": "https://static.wikia.nocookie.net/tensei-shitara/images/3/3a/Lucia.png"
  },
  {
    "id": 75,
    "name": "Velgrynd (ally Demon Lord)",
    "rarity": "Legendary",
    "price": 750,
    "faction": "Demon Lords",
    "image_url": "https://static.wikia.nocookie.net/tensei-shitara/images/4/4a/Velgrynd.png"
  },
  {
    "id": 76,
    "name": "Velzard (ally Demon Lord)",
    "rarity": "Legendary",
    "price": 750,
    "faction": "Demon Lords",
    "image_url": "https://static.wikia.nocookie.net/tensei-shitara/images/5/5a/Velzard.png"
  },
  {
    "id": 77,
    "name": "Velgaia",
    "rarity": "Legendary",
    "price": 750,
    "faction": "Demon Lords",
    "image_url": "https://static.wikia.nocookie.net/tensei-shitara/images/6/6a/Velgaia.png"
  },
  {
    "id": 78,
    "name": "Velda",
    "rarity": "Legendary",
    "price": 800,
    "faction": "Demon Lords",
    "image_url": "https://static.wikia.nocookie.net/tensei-shitara/images/7/7a/Velda.png"
  },
  {
    "id": 79,
    "name": "Lucifer",
    "rarity": "Legendary",
    "price": 800,
    "faction": "Demon Lords",
    "image_url": "https://static.wikia.nocookie.net/tensei-shitara/images/8/8a/Lucifer.png"
  },
  {
    "id": 80,
    "name": "Beelzebub",
    "rarity": "Legendary",
    "price": 800,
    "faction": "Demon Lords",
    "image_url": "https://static.wikia.nocookie.net/tensei-shitara/images/9/9a/Beelzebub.png"
  },
  {
    "id": 81,
    "name": "Mammon",
    "rarity": "Legendary",
    "price": 800,
    "faction": "Demon Lords",
    "image_url": "https://static.wikia.nocookie.net/tensei-shitara/images/1/1a/Mammon.png"
  },
  {
    "id": 82,
    "name": "Belphegor",
    "rarity": "Legendary",
    "price": 800,
    "faction": "Demon Lords",
    "image_url": "https://static.wikia.nocookie.net/tensei-shitara/images/2/2a/Belphegor.png"
  },
  {
    "id": 83,
    "name": "Asmodeus",
    "rarity": "Legendary",
    "price": 800,
    "faction": "Demon Lords",
    "image_url": "https://static.wikia.nocookie.net/tensei-shitara/images/3/3a/Asmodeus.png"
  },
  {
    "id": 84,
    "name": "Satan",
    "rarity": "Legendary",
    "price": 800,
    "faction": "Demon Lords",
    "image_url": "https://static.wikia.nocookie.net/tensei-shitara/images/4/4a/Satan.png"
  },
  {
    "id": 85,
    "name": "Lucian",
    "rarity": "Epic",
    "price": 400,
    "faction": "Demon Lords",
    "image_url": "https://static.wikia.nocookie.net/tensei-shitara/images/5/5a/Lucian.png"
  },
  {
    "id": 86,
    "name": "Belial",
    "rarity": "Legendary",
    "price": 800,
    "faction": "Demon Lords",
    "image_url": "https://static.wikia.nocookie.net/tensei-shitara/images/6/6a/Belial.png"
  },
  {
    "id": 87,
    "name": "Astaroth",
    "rarity": "Legendary",
    "price": 800,
    "faction": "Demon Lords",
    "image_url": "https://static.wikia.nocookie.net/tensei-shitara/images/7/7a/Astaroth.png"
  },
  {
    "id": 88,
    "name": "Lilith",
    "rarity": "Epic",
    "price": 400,
    "faction": "Demon Lords",
    "image_url": "https://static.wikia.nocookie.net/tensei-shitara/images/l/lc/Lilith.png"
  },
  {
    "id": 89,
    "name": "Belzebuth",
    "rarity": "Legendary",
    "price": 800,
    "faction": "Demon Lords",
    "image_url": "https://static.wikia.nocookie.net/tensei-shitara/images/b/bz/Belzebuth.png"
  },
  {
    "id": 90,
    "name": "Lucifina",
    "rarity": "Epic",
    "price": 420,
    "faction": "Demon Lords",
    "image_url": "https://static.wikia.nocookie.net/tensei-shitara/images/l/lf/Lucifina.png"
  },
  {
    "id": 91,
    "name": "Amon",
    "rarity": "Legendary",
    "price": 750,
    "faction": "Demon Lords",
    "image_url": "https://static.wikia.nocookie.net/tensei-shitara/images/a/am/Amon.png"
  },
  {
    "id": 92,
    "name": "Barbatos",
    "rarity": "Epic",
    "price": 420,
    "faction": "Demon Lords",
    "image_url": "https://static.wikia.nocookie.net/tensei-shitara/images/b/bt/Barbatos.png"
  },
  {
    "id": 93,
    "name": "Marchosias",
    "rarity": "Rare",
    "price": 300,
    "faction": "Demon Lords",
    "image_url": "https://static.wikia.nocookie.net/tensei-shitara/images/m/ms/Marchosias.png"
  },
  {
    "id": 94,
    "name": "Phenex",
    "rarity": "Epic",
    "price": 380,
    "faction": "Demon Lords",
    "image_url": "https://static.wikia.nocookie.net/tensei-shitara/images/p/px/Phenex.png"
  },
  {
    "id": 95,
    "name": "Valefor",
    "rarity": "Rare",
    "price": 280,
    "faction": "Demon Lords",
    "image_url": "https://static.wikia.nocookie.net/tensei-shitara/images/v/vf/Valefor.png"
  },
  {
    "id": 96,
    "name": "Forneus",
    "rarity": "Rare",
    "price": 280,
    "faction": "Demon Lords",
    "image_url": "https://static.wikia.nocookie.net/tensei-shitara/images/f/fs/Forneus.png"
  },
  {
    "id": 97,
    "name": "Glasya-Labolas",
    "rarity": "Epic",
    "price": 400,
    "faction": "Demon Lords",
    "image_url": "https://static.wikia.nocookie.net/tensei-shitara/images/g/gl/Glasya.png"
  },
  {
    "id": 98,
    "name": "Baal",
    "rarity": "Legendary",
    "price": 800,
    "faction": "Demon Lords",
    "image_url": "https://static.wikia.nocookie.net/tensei-shitara/images/b/bl/Baal.png"
  },
  {
    "id": 99,
    "name": "Paimon",
    "rarity": "Legendary",
    "price": 800,
    "faction": "Demon Lords",
    "image_url": "https://static.wikia.nocookie.net/tensei-shitara/images/p/pm/Paimon.png"
  },
  {
    "id": 100,
    "name": "Stolas",
    "rarity": "Epic",
    "price": 420,
    "faction": "Demon Lords",
    "image_url": "https://static.wikia.nocookie.net/tensei-shitara/images/s/sl/Stolas.png"
  }
]
   
